unblob_native-0.1.6.dist-info/METADATA
unblob_native-0.1.6.dist-info/WHEEL
unblob_native-0.1.6.dist-info/licenses/LICENSE
unblob_native.libs/libgcc_s-4e37474d.so.1
unblob_native/py.typed
unblob_native/math_tools.pyi
unblob_native/__init__.py
unblob_native/sandbox.pyi
unblob_native/_native.abi3.so
unblob_native-0.1.6.dist-info/RECORD
