Metadata-Version: 2.4
Name: unblob-native
Version: 0.1.6
License-File: LICENSE
Summary: Performance-critical functionality for Unblob
Author-email: ONEKEY <support@onekey.com>
License: MIT
Requires-Python: >=3.9
Project-URL: homepage, https://unblob.org
Project-URL: repository, https://github.com/onekey-sec/unblob-native
